{
  "metadata": {
    "title": "Core Public Event Vocabulary",
    "uri": "http://data.europa.eu/m8g",
    "issued": "2024-05-06",
    "filename": "core-public-event",
    "navigation": {
      "self": "https://semiceu.github.io/doc/vocabularium/cpev"
    },
    "license": "https://creativecommons.org/licenses/by/4.0/",
    "documenttype": "voc",
    "documentconfig": {},
    "status": "Semic Recommendation",
    "statuslabel": "Onbekend",
    "repositoryurl": "git@uri.semic.eu-thema:SEMICeu/uri.semic.eu-thema.git/tree/8894fe08f0242868db3e2bf5af637b45fbc1d2a0",
    "changelogurl": "git@uri.semic.eu-thema:SEMICeu/uri.semic.eu-thema.git/blob/8894fe08f0242868db3e2bf5af637b45fbc1d2a0/CHANGELOG",
    "feedbackurl": "https://github.com/SEMICeu/Core-Public-Event-Vocabulary/issues",
    "standaardregisterurl": "https://github.com/SEMICeu/Core-Public-Event-Vocabulary/blob/master/releases/1.1.0/Changelog.md",
    "usesVocs": [],
    "usesAPs": []
  },
  "classes": [
    {
      "uri": "http://data.europa.eu/m8g/ContactPoint",
      "name": "ContactPoint",
      "label": {
        "en": "Contact Point"
      },
      "sort": "Contact Point",
      "description": {
        "en": "Information (e.g. e-mail address, telephone number) of a person or department through which the user can get in touch with."
      },
      "usage": {
        "en": "The Core Public Organization Vocabulary defines properties for telephone number, e-mail address and opening hours although it is noteworthy that the class is based on schema.org's <a href=\"http://schema.org/ContactPoint\"> ContactPoint </a> class  that has additional properties that some implementations may find useful."
      },
      "equivalent": [],
      "parents": []
    },
    {
      "uri": "http://data.europa.eu/m8g/Participation",
      "name": "Participation",
      "label": {
        "en": "Participation"
      },
      "sort": "Participation",
      "description": {
        "en": "The Participation class allows to define roles within a certain context."
      },
      "usage": {},
      "equivalent": [],
      "parents": []
    },
    {
      "uri": "http://data.europa.eu/m8g/PublicEvent",
      "name": "PublicEvent",
      "label": {
        "en": "Public Event"
      },
      "sort": "Public Event",
      "description": {
        "en": "Something that happens at a particular place and time,\r\norganised by one or more agents for a particular purpose, and is of interest to a general\r\n audience. This definition excludes natural events such as earthquakes and volcanic \r\neruptions."
      },
      "usage": {},
      "equivalent": [],
      "parents": []
    }
  ],
  "properties": [
    {
      "uri": "http://data.europa.eu/m8g/accessibility",
      "name": "accessibility",
      "label": {
        "en": "accessibility"
      },
      "sort": "accessibility",
      "description": {
        "en": "Information about how the Public Event can be approached, reached or entered, in particular for people with special needs."
      },
      "usage": {
        "en": "This property may be provided in multiple languages with multiple instances of the accessibility property."
      },
      "domain": [
        "http://data.europa.eu/m8g/PublicEvent"
      ],
      "range": [
        "http://www.w3.org/1999/02/22-rdf-syntax-ns#langString"
      ],
      "parents": []
    },
    {
      "uri": "http://data.europa.eu/m8g/audience",
      "name": "audience",
      "label": {
        "en": "audience"
      },
      "sort": "audience",
      "description": {
        "en": "The target group of people for whom the Public Event is created."
      },
      "usage": {},
      "domain": [
        "http://data.europa.eu/m8g/PublicEvent"
      ],
      "range": [
        "http://www.w3.org/2004/02/skos/core#Concept"
      ],
      "parents": []
    },
    {
      "uri": "http://data.europa.eu/m8g/contactPage",
      "name": "contactPage",
      "label": {
        "en": "contact page"
      },
      "sort": "contact page",
      "description": {
        "en": "A web page that could be used to reach out the Contact Point."
      },
      "usage": {},
      "domain": [
        "http://data.europa.eu/m8g/ContactPoint"
      ],
      "range": [
        "http://xmlns.com/foaf/0.1/Document"
      ],
      "parents": []
    },
    {
      "uri": "http://data.europa.eu/m8g/email",
      "name": "hasEmail",
      "label": {
        "en": "has email"
      },
      "sort": "has email",
      "description": {
        "en": "An electronic address through which the Contact Point can be contacted."
      },
      "usage": {},
      "domain": [
        "http://data.europa.eu/m8g/ContactPoint"
      ],
      "range": [
        "http://www.w3.org/2000/01/rdf-schema#Literal"
      ],
      "parents": []
    },
    {
      "uri": "http://data.europa.eu/m8g/eventNumber",
      "name": "eventNumber",
      "label": {
        "en": "event number"
      },
      "sort": "event number",
      "description": {
        "en": "The sequence position of the Public Event."
      },
      "usage": {
        "en": "Examples could be the ''4th\" or \"2022\"."
      },
      "domain": [
        "http://data.europa.eu/m8g/PublicEvent"
      ],
      "range": [
        "http://www.w3.org/1999/02/22-rdf-syntax-ns#langString"
      ],
      "parents": []
    },
    {
      "uri": "http://data.europa.eu/m8g/eventStatus",
      "name": "eventStatus",
      "label": {
        "en": "event status"
      },
      "sort": "event status",
      "description": {
        "en": " This property defines the overall status of the event."
      },
      "usage": {
        "en": "The recomended code list is the <a href=\"https://op.europa.eu/en/web/eu-vocabularies/concept-scheme/-/resource?uri=http://publications.europa.eu/resource/authority/event-status\">  Event Status Controlled vocabulary </a> maintained by the Publications Office of the EU."
      },
      "domain": [
        "http://data.europa.eu/m8g/PublicEvent"
      ],
      "range": [
        "http://www.w3.org/2004/02/skos/core#Concept"
      ],
      "parents": []
    },
    {
      "uri": "http://data.europa.eu/m8g/expectedNumberOfParticipants",
      "name": "expectedNumberOfParticipants",
      "label": {
        "en": "expected number of participants"
      },
      "sort": "expected number of participants",
      "description": {
        "en": "The number of participants expected to participate in the event."
      },
      "usage": {},
      "domain": [
        "http://data.europa.eu/m8g/PublicEvent"
      ],
      "range": [
        "http://www.w3.org/2001/XMLSchema#integer"
      ],
      "parents": []
    },
    {
      "uri": "http://data.europa.eu/m8g/format",
      "name": "format",
      "label": {
        "en": "format"
      },
      "sort": "format",
      "description": {
        "en": "A plan of organisation or arrangement of the Public Event."
      },
      "usage": {
        "en": "Examples include conference call, physical meeting or hybrid."
      },
      "domain": [
        "http://data.europa.eu/m8g/PublicEvent"
      ],
      "range": [
        "http://www.w3.org/2004/02/skos/core#Concept"
      ],
      "parents": []
    },
    {
      "uri": "http://data.europa.eu/m8g/frequency",
      "name": "frequency",
      "label": {
        "en": "frequency"
      },
      "sort": "frequency",
      "description": {
        "en": "The recurrence of an instant or period."
      },
      "usage": {
        "en": "It is recommended to use the frequency from an existing vocabulary like the <a href=\"https://op.europa.eu/en/web/eu-vocabularies/concept-scheme/-/resource?uri=http://publications.europa.eu/resource/authority/frequency\">Frequency</a> from the Publications Office."
      },
      "domain": [
        "http://www.w3.org/2006/time#TemporalEntity"
      ],
      "range": [
        "http://www.w3.org/2004/02/skos/core#Concept"
      ],
      "parents": []
    },
    {
      "uri": "http://data.europa.eu/m8g/registrationPage",
      "name": "registrationPage",
      "label": {
        "en": "registration page"
      },
      "sort": "registration page",
      "description": {
        "en": "A web page that provides means to attend the Public Event."
      },
      "usage": {},
      "domain": [
        "http://data.europa.eu/m8g/PublicEvent"
      ],
      "range": [
        "http://xmlns.com/foaf/0.1/Document"
      ],
      "parents": []
    },
    {
      "uri": "http://data.europa.eu/m8g/role",
      "name": "role",
      "label": {
        "en": "role"
      },
      "sort": "role",
      "description": {
        "en": "The function of an Agent within a Participation."
      },
      "usage": {},
      "domain": [
        "http://data.europa.eu/m8g/Participation"
      ],
      "range": [
        "http://www.w3.org/2004/02/skos/core#Concept"
      ],
      "parents": []
    },
    {
      "uri": "http://data.europa.eu/m8g/telephone",
      "name": "hasTelephone",
      "label": {
        "en": "has telephone"
      },
      "sort": "has telephone",
      "description": {
        "en": "A telephone number through which the Contact Point can be contacted."
      },
      "usage": {},
      "domain": [
        "http://data.europa.eu/m8g/ContactPoint"
      ],
      "range": [
        "http://www.w3.org/2000/01/rdf-schema#Literal"
      ],
      "parents": []
    }
  ],
  "contributors": [
    {
      "role": "A",
      "first_name": "Core Vocabularies Working Group",
      "affiliation": {}
    },
    {
      "role": "E",
      "first_name": "Florian",
      "last_name": "Barthelemy",
      "affiliation": {
        "name": "PwC EU Services"
      }
    },
    {
      "role": "E",
      "first_name": "Jitse",
      "last_name": "De Cock",
      "affiliation": {
        "name": "PwC EU Services"
      }
    },
    {
      "role": "E",
      "first_name": "Emiel",
      "last_name": "Dhondt",
      "affiliation": {
        "name": "PwC EU Services"
      }
    },
    {
      "role": "E",
      "first_name": "Pavlina",
      "last_name": "Fragkou",
      "affiliation": {
        "name": "European Commission"
      }
    },
    {
      "role": "E",
      "first_name": "Arthur",
      "last_name": "Schiltz",
      "affiliation": {
        "name": "PwC EU Services"
      }
    },
    {
      "role": "E",
      "first_name": "Anastasia",
      "last_name": "Sofou",
      "affiliation": {
        "name": "Trasys International"
      }
    },
    {
      "role": "E",
      "first_name": "Emidio",
      "last_name": "Stani",
      "affiliation": {
        "name": "PwC EU Services"
      }
    },
    {
      "role": "E",
      "first_name": "Bert",
      "last_name": "Van Nuffelen",
      "affiliation": {}
    }
  ],
  "external_terms": [
    {
      "uri": "http://data.europa.eu/m8g/hasNextEvent",
      "name": "hasNextEvent",
      "label": {
        "en": "has next event"
      },
      "description": {
        "en": "The Public Event that comes after this one."
      },
      "usage": {},
      "sort": "has next event",
      "inscope": true,
      "indvl": false,
      "inpackage": false,
      "show": true
    },
    {
      "uri": "http://data.europa.eu/m8g/hasPreviousEvent",
      "name": "hasPreviousEvent",
      "label": {
        "en": "has previous event"
      },
      "description": {
        "en": "The Public Event that comes before this one."
      },
      "usage": {},
      "sort": "has previous event",
      "inscope": true,
      "indvl": false,
      "inpackage": false,
      "show": true
    },
    {
      "uri": "http://data.europa.eu/m8g/parentEvent",
      "name": "parentEvent",
      "label": {
        "en": "parent event"
      },
      "description": {
        "en": "A relation to another Public Event that encompasses it."
      },
      "usage": {},
      "sort": "parent event",
      "inscope": true,
      "indvl": false,
      "inpackage": false,
      "show": true
    },
    {
      "uri": "http://data.europa.eu/m8g/subEvent",
      "name": "subEvent",
      "label": {
        "en": "sub event"
      },
      "description": {
        "en": "A relation towards another Public Event that belong to it."
      },
      "usage": {},
      "sort": "sub event",
      "inscope": true,
      "indvl": false,
      "inpackage": false,
      "show": true
    },
    {
      "uri": "http://purl.org/dc/terms/description",
      "name": "description",
      "label": {
        "en": "description"
      },
      "description": {
        "en": "A textual explanation of the Pulblic Event."
      },
      "usage": {
        "en": "Descriptions may be provided in multiple languages with multiple instances of the description property."
      },
      "sort": "description",
      "inscope": true,
      "indvl": false,
      "inpackage": false,
      "show": true
    },
    {
      "uri": "http://purl.org/dc/terms/identifier",
      "name": "identifier",
      "label": {
        "en": "identifier"
      },
      "description": {
        "en": "The unambiguous structured reference for the Public Event."
      },
      "usage": {},
      "sort": "identifier",
      "inscope": true,
      "indvl": false,
      "inpackage": false,
      "show": true
    },
    {
      "uri": "http://purl.org/dc/terms/language",
      "name": "language",
      "label": {
        "en": "language"
      },
      "description": {
        "en": "The language in which the Public Event is given."
      },
      "usage": {
        "en": "The recommended controlled vocabularies for this property is the <a href=\" https://op.europa.eu/en/web/eu-vocabularies/concept-scheme/-/resource?uri=http://publications.europa.eu/resource/authority/language\">Language</a> Authority Table of the Publications Office."
      },
      "sort": "language",
      "inscope": true,
      "indvl": false,
      "inpackage": false,
      "show": true
    },
    {
      "uri": "http://purl.org/dc/terms/subject",
      "name": "topic",
      "label": {
        "en": "topic"
      },
      "description": {
        "en": "The subject of the Public Event."
      },
      "usage": {
        "en": "Examples include culture, sport or tourism."
      },
      "sort": "topic",
      "inscope": true,
      "indvl": false,
      "inpackage": false,
      "show": true
    },
    {
      "uri": "http://purl.org/dc/terms/title",
      "name": "title",
      "label": {
        "en": "title"
      },
      "description": {
        "en": "The name given to the Public Event."
      },
      "usage": {
        "en": "Titles may be provided in multiple languages with multiple instances of the title property."
      },
      "sort": "title",
      "inscope": true,
      "indvl": false,
      "inpackage": false,
      "show": true
    },
    {
      "uri": "http://purl.org/dc/terms/type",
      "name": "eventType",
      "label": {
        "en": "event type"
      },
      "description": {
        "en": "The nature or genre of the Public Event. "
      },
      "usage": {
        "en": "Examples include conferences and summits, meetings, exhibitions, and public debates. The eventType property links the event to a SKOS Concept that provides a classification.\r\n\r\nAn existing classification from Publications Office could be used, see <a href=\"\r\nhttps://op.europa.eu/en/web/eu-vocabularies/dataset/-/resource?uri=http://publications.europa.eu/resource/dataset/public-event-type\">Public Event Type</a>."
      },
      "sort": "event type",
      "inscope": true,
      "indvl": false,
      "inpackage": false,
      "show": true
    },
    {
      "uri": "http://www.w3.org/ns/locn#address",
      "name": "address",
      "label": {
        "en": "address"
      },
      "description": {
        "en": "Associates any Resource with the corresponding Address."
      },
      "usage": {
        "en": "Asserting the address relationship implies that the\r\n Resource has an Address."
      },
      "sort": "address",
      "inscope": true,
      "indvl": false,
      "inpackage": false,
      "show": true
    },
    {
      "uri": "http://xmlns.com/foaf/0.1/homepage",
      "name": "homepage",
      "label": {
        "en": "homepage"
      },
      "description": {
        "en": "The website of the Public Event."
      },
      "usage": {
        "en": "The value of this property is a URL."
      },
      "sort": "homepage",
      "inscope": true,
      "indvl": false,
      "inpackage": false,
      "show": true
    }
  ],
  "documentroot": "/doc/vocabularium/cpev"
}
